odoo/addons/mail_autosubscribe/README.rst
odoo/addons/mail_autosubscribe/__init__.py
odoo/addons/mail_autosubscribe/__manifest__.py
odoo/addons/mail_autosubscribe/i18n/ca.po
odoo/addons/mail_autosubscribe/i18n/es.po
odoo/addons/mail_autosubscribe/i18n/it.po
odoo/addons/mail_autosubscribe/i18n/mail_autosubscribe.pot
odoo/addons/mail_autosubscribe/models/__init__.py
odoo/addons/mail_autosubscribe/models/mail_autosubscribe.py
odoo/addons/mail_autosubscribe/models/mail_template.py
odoo/addons/mail_autosubscribe/models/mail_thread.py
odoo/addons/mail_autosubscribe/models/models.py
odoo/addons/mail_autosubscribe/models/res_partner.py
odoo/addons/mail_autosubscribe/readme/CONFIGURE.rst
odoo/addons/mail_autosubscribe/readme/CONTRIBUTORS.rst
odoo/addons/mail_autosubscribe/readme/DESCRIPTION.rst
odoo/addons/mail_autosubscribe/readme/ROADMAP.rst
odoo/addons/mail_autosubscribe/security/ir.model.access.csv
odoo/addons/mail_autosubscribe/static/description/icon.png
odoo/addons/mail_autosubscribe/static/description/index.html
odoo/addons/mail_autosubscribe/tests/__init__.py
odoo/addons/mail_autosubscribe/tests/test_mail_autosubscribe.py
odoo/addons/mail_autosubscribe/tests/models/__init__.py
odoo/addons/mail_autosubscribe/tests/models/fake_order.py
odoo/addons/mail_autosubscribe/views/mail_autosubscribe.xml
odoo/addons/mail_autosubscribe/views/mail_template.xml
odoo/addons/mail_autosubscribe/views/res_partner.xml
odoo14_addon_mail_autosubscribe-14.0.1.0.1.dev12.dist-info/METADATA
odoo14_addon_mail_autosubscribe-14.0.1.0.1.dev12.dist-info/WHEEL
odoo14_addon_mail_autosubscribe-14.0.1.0.1.dev12.dist-info/top_level.txt
odoo14_addon_mail_autosubscribe-14.0.1.0.1.dev12.dist-info/RECORD
